setup.py
gaw/__init__.py
gaw/entrypoint.py
gaw/gawclient.py
gaw/gawserver.py
gaw.egg-info/PKG-INFO
gaw.egg-info/SOURCES.txt
gaw.egg-info/dependency_links.txt
gaw.egg-info/entry_points.txt
gaw.egg-info/requires.txt
gaw.egg-info/top_level.txt
gaw/cli/__init__.py
gaw/cli/servicerunner.py
gaw/jsonsocketserver/__init__.py
gaw/jsonsocketserver/client.py
gaw/jsonsocketserver/datatype.py
gaw/jsonsocketserver/exceptions.py
gaw/jsonsocketserver/server.py
gaw/postoffice/__init__.py
gaw/postoffice/client.py
gaw/postoffice/core.py
gaw/postoffice/exceptions.py
gaw/postoffice/server.py
gaw/serializable/__init__.py
gaw/serializable/exceptions.py
gaw/serializable/serializable.py