Metadata-Version: 1.0
Name: gaw
Version: 0.7.5
Summary: A small library that helps you developing microservices over simple TCP socket with ease
Home-page: https://github.com/phizaz/gaw
Author: Konpat Preechakul
Author-email: the.akita.ta@gmail.com
License: UNKNOWN
Keywords: microservice
Platform: UNKNOWN
